{%- set MANAGER = salt['grains.get']('master') -%}
{%- set SENSORONIKEY = salt['pillar.get']('static:sensoronikey', '') -%}
{
  "logFilename": "/opt/sensoroni/logs/sensoroni.log",
  "logLevel":"debug",
  "agent": {
    "pollIntervalMs": 10000,
    "serverUrl": "https://{{ MANAGER }}/sensoroniagents",
    "verifyCert": false,
    "modules": {
      "statickeyauth": {
        "apiKey": "{{ SENSORONIKEY }}"
      },
      "stenoquery": {
        "executablePath": "/opt/sensoroni/scripts/stenoquery.sh",
        "pcapInputPath": "/nsm/pcap",
        "pcapOutputPath": "/nsm/pcapout"
      }
    }
  }
}
